astrohelper/__init__.py
astrohelper/functions.py
astrohelper-0.1.3.dist-info/licenses/LICENSE.md
astrohelper-0.1.3.dist-info/METADATA
astrohelper-0.1.3.dist-info/WHEEL
astrohelper-0.1.3.dist-info/top_level.txt
astrohelper-0.1.3.dist-info/RECORD
