Metadata-Version: 2.4
Name: astrohelper
Version: 0.1.3
Summary: A Python package helping with astronomical observations
Author-email: Justus Sponbrucker <justus.sponbrucker@fau.de>, Dorian Pejic <dorian.pejic@fau.de>
Project-URL: Homepage, https://github.com/DP0604/AstroObjectHelperPipeline
Keywords: astronomy,astrophysics,data analysis,visualization,astroquery,astroplan
Requires-Python: >=3.8
License-File: LICENSE.md
Requires-Dist: numpy
Requires-Dist: astropy
Requires-Dist: astroquery
Requires-Dist: astroplan
Requires-Dist: cartopy
Requires-Dist: matplotlib
Requires-Dist: scipy
Requires-Dist: pytz
Dynamic: license-file
